lrcparser/__init__.py
lrcparser/constants.py
lrcparser/file.py
lrcparser/line.py
lrcparser/parser.py
lrcparser/text.py
lrcparser/time.py
lrcparser/types.py
lrcparser/utils.py
lrcparser-0.1.2.dist-info/LICENSE
lrcparser-0.1.2.dist-info/METADATA
lrcparser-0.1.2.dist-info/WHEEL
lrcparser-0.1.2.dist-info/top_level.txt
lrcparser-0.1.2.dist-info/RECORD
