Metadata-Version: 2.1
Name: lrcparser
Version: 0.1.2
Summary: A simple lyric file parser
Author-email: 283375 <log_283375@163.com>
Project-URL: Homepage, https://github.com/283375/lrcparser_python
Project-URL: Bug Tracker, https://github.com/283375/lrcparser_python/issues
Classifier: Development Status :: 3 - Alpha
Classifier: Programming Language :: Python :: 3
Classifier: License :: OSI Approved :: MIT License
Requires-Python: >=3.8
License-File: LICENSE
